gpt_agents_py/__init__.py
gpt_agents_py/extensions/anthropic_llm_caller.py
gpt_agents_py/gpt_agents.py
gpt_agents_py-0.1.15.dist-info/LICENSE
gpt_agents_py-0.1.15.dist-info/METADATA
gpt_agents_py-0.1.15.dist-info/WHEEL
gpt_agents_py-0.1.15.dist-info/RECORD
