Metadata-Version: 2.3
Name: gpt_agents_py
Version: 0.1.15
Summary: 
License: MIT
Author: James Delancey
Author-email: jamesdelanceyjr@gmail.com
Requires-Python: >=3.11
Classifier: License :: OSI Approved :: MIT License
Classifier: Programming Language :: Python :: 3
Classifier: Programming Language :: Python :: 3.11
Classifier: Programming Language :: Python :: 3.12
Classifier: Programming Language :: Python :: 3.13
